inaturalist_to_ankivalenz/__init__.py
inaturalist_to_ankivalenz/api.py
inaturalist_to_ankivalenz/cli.py
inaturalist_to_ankivalenz/markdown.py
inaturalist_to_ankivalenz-0.3.0.dist-info/METADATA
inaturalist_to_ankivalenz-0.3.0.dist-info/WHEEL
inaturalist_to_ankivalenz-0.3.0.dist-info/entry_points.txt
inaturalist_to_ankivalenz-0.3.0.dist-info/RECORD
