Metadata-Version: 2.4
Name: inaturalist-to-ankivalenz
Version: 0.3.0
Summary: Export iNaturalist observations to Ankivalenz-formatted Markdown for creating flashcards
Author-email: Harry Vangberg <harry@vangberg.name>
License-Expression: MIT
Requires-Python: >=3.8
Requires-Dist: click>=8.1.7
Requires-Dist: requests>=2.31.0
